straxen/__init__.py
straxen/analyses/__init__.py
straxen/analyses/bokeh_waveform_plot.py
straxen/analyses/daq_waveforms.py
straxen/analyses/event_display.py
straxen/analyses/holoviews_waveform_display.py
straxen/analyses/pulse_plots.py
straxen/analyses/quick_checks.py
straxen/analyses/records_matrix.py
straxen/analyses/waveform_plot.py
straxen/bokeh_utils.py
straxen/common.py
straxen/config/__init__.py
straxen/config/check_global_version.py
straxen/config/check_superruns.py
straxen/config/config_tests.py
straxen/config/preprocessors.py
straxen/config/protocols.py
straxen/config/regex_dispatcher.py
straxen/config/url_config.py
straxen/contexts.py
straxen/daq_core.py
straxen/docs_utils.py
straxen/entry_points.py
straxen/holoviews/__init__.py
straxen/holoviews/holoviews_inspector.py
straxen/holoviews/holoviews_peak_data.py
straxen/holoviews/holoviews_pmt_array.py
straxen/holoviews/holoviews_tpc_event_display.py
straxen/holoviews_utils.py
straxen/itp_map.py
straxen/matplotlib_utils.py
straxen/mini_analysis.py
straxen/misc.py
straxen/numbafied_scipy.py
straxen/plugins/README.md
straxen/plugins/__init__.py
straxen/plugins/afterpulses/__init__.py
straxen/plugins/afterpulses/afterpulse_processing.py
straxen/plugins/aqmon_hits/__init__.py
straxen/plugins/aqmon_hits/aqmon_hits.py
straxen/plugins/defaults.py
straxen/plugins/events/__init__.py
straxen/plugins/events/_event_s1_positions_base.py
straxen/plugins/events/_event_s2_positions_base.py
straxen/plugins/events/corrected_areas.py
straxen/plugins/events/distinct_channels.py
straxen/plugins/events/energy_estimates.py
straxen/plugins/events/event_ambience.py
straxen/plugins/events/event_area_per_channel.py
straxen/plugins/events/event_basics_som.py
straxen/plugins/events/event_basics_vanilla.py
straxen/plugins/events/event_info.py
straxen/plugins/events/event_info_double.py
straxen/plugins/events/event_nearest_triggering.py
straxen/plugins/events/event_pattern_fit.py
straxen/plugins/events/event_position_uncertainty.py
straxen-3.2.7.dist-info/METADATA
straxen-3.2.7.dist-info/WHEEL
straxen-3.2.7.dist-info/entry_points.txt
straxen-3.2.7.dist-info/licenses/LICENSE
straxen-3.2.7.dist-info/RECORD
