Metadata-Version: 2.4
Name: straxen
Version: 3.2.7
Summary: Streaming analysis for XENON
License-File: LICENSE
Author: Straxen contributors, the XENON collaboration
Requires-Python: >=3.10,<3.13
Classifier: Development Status :: 5 - Production/Stable
Classifier: Intended Audience :: Science/Research
Classifier: License :: OSI Approved :: BSD License
Classifier: Natural Language :: English
Classifier: Programming Language :: Python :: 3
Classifier: Programming Language :: Python :: 3.10
Classifier: Programming Language :: Python :: 3.11
Classifier: Programming Language :: Python :: 3.12
Classifier: Programming Language :: Python :: Implementation :: CPython
Classifier: Topic :: Scientific/Engineering :: Physics
Provides-Extra: docs
Requires-Dist: Jinja2 (==3.1.5) ; extra == "docs"
Requires-Dist: bokeh
Requires-Dist: commentjson
Requires-Dist: commonmark (==0.9.1) ; extra == "docs"
Requires-Dist: docutils (==0.18.1)
Requires-Dist: gitpython
Requires-Dist: graphviz
Requires-Dist: immutabledict
Requires-Dist: lxml_html_clean ; extra == "docs"
Requires-Dist: m2r (==0.2.1)
Requires-Dist: matplotlib
Requires-Dist: mistune (==0.8.4)
Requires-Dist: multihist (>=0.6.3)
Requires-Dist: nbsphinx (==0.8.9) ; extra == "docs"
Requires-Dist: numba (>=0.50.0)
Requires-Dist: numpy
Requires-Dist: packaging
Requires-Dist: pymongo
Requires-Dist: recommonmark (==0.7.1) ; extra == "docs"
Requires-Dist: requests
Requires-Dist: sphinx (==7.1.2) ; extra == "docs"
Requires-Dist: sphinx_rtd_theme (==1.3.0) ; extra == "docs"
Requires-Dist: strax (>=2.2.1)
Requires-Dist: urllib3 (==2.2.2) ; extra == "docs"
Requires-Dist: utilix (>=0.11.0)
Requires-Dist: xedocs (>=0.2.41)
Project-URL: Repository, https://github.com/XENONnT/straxen
